{
  "initialUrl": "https://automatetube.com/",
  "initialResearchSummary": "Alright, let’s break this down like we’re just hanging out and rapping about what this website is all about. So, we’re looking at **AutomateTube**, which is all about helping you create videos using some AI magic. Think of it as your go-to spot for generating videos without having to stress over filming, editing, or any of that tedious stuff. It’s like having your own video production team, but just way easier and faster.\n\n### What’s the Deal with AutomateTube?\n\nThe main point of AutomateTube is to offer an **AI Video Generator**. This means you can whip up videos by simply providing some input to the AI, and it’ll handle the heavy lifting. Whether you're a content creator, a marketer, or just someone who wants to put together fun videos, this site is geared towards making that process super streamlined.\n\n### What Are They Selling?\n\nWhile they don’t explicitly list out all the features on the site, reading between the lines, you can expect a few things:\n\n1. **Video Creation Tools**: The \"Create Video\" feature suggests you can make videos in a few clicks. It’s all about automation, so you can crank out content without the usual hassle.\n  \n2. **Video Listings**: There’s a mention of “listing videos,” which likely means you can organize or showcase different videos you’ve created on the platform. This is pretty handy if you’re building a portfolio or just trying to keep your work nice and tidy.\n\n### Key Topics and Features\n\nNow, let’s dive into some key areas mentioned in their content. \n\n#### Information Collection\n\nThis part is pretty important because it lets you know what info they’re collecting from you if you decide to sign up:\n\n- **Personal Info**: You’ll need to share basic stuff like your name, email address, and any billing info if you’re going to be paying for services. They also mention account credentials, which is just your login stuff.\n  \n- **Automatically Collected Info**: They’re gathering data like your IP address, device info, browser type, and even usage patterns. Basically, they’re keeping tabs on how you interact with the site.\n\n#### How They Use Your Info\n\nThey’re pretty upfront about how they use your info:\n\n- **To Improve Services**: They’re using the info to better the platform. Think of it as them gathering feedback to make things smoother and more user-friendly.\n  \n- **Processing Payments and Communication**: If you’re buying anything, they need your info to handle those transactions and keep you in the loop about any updates or services.\n\n- **Personalizing Your Experience**: They’re all about making your user experience unique, tailoring it to your preferences.\n\n#### Sharing Your Info\n\nYou know how some websites sell your data? Not these guys. They promise not to sell your personal information. However, they might share it with:\n\n- **Service Providers**: Companies that help them run their operations might get access to your info to provide support.\n  \n- **Legal Authorities**: If the law comes knocking, they might have to share your info.\n\n- **With Your Consent**: They’ll check in with you if they need to share information with other parties.\n\n#### Keeping Your Data Safe\n\nThey talk a good game about data security, which is reassuring. Here’s what they’re doing to keep your information safe:\n\n- **Encryption**: Sensitive data is encrypted, meaning it’s turned into unreadable code to protect it.\n  \n- **Regular Security Assessments**: They’re regularly checking to make sure their security measures are up to snuff.\n\n- **Access Controls**: Only certain people can access your data, limiting who sees what.\n\n#### Your Rights\n\nYou’ve got rights as a user, and they lay them out pretty clearly:\n\n- **Access Your Data**: You can see what data they have on you.\n  \n- **Correct Your Data**: If something’s wrong, you can fix it.\n  \n- **Request Deletion**: Want to delete your data? You can ask for that.\n\n- **Opting Out**: If you don’t want them to send you marketing stuff, you can opt-out.\n\n- **Export Your Data**: You can take your info and run if you want to leave.\n\n#### Cookies and Tracking\n\nSo, what’s up with cookies? They use cookies and similar tech to:\n\n- **Maintain Your Session**: This means keeping you logged in and remembering what you were doing.\n  \n- **Analyze Usage**: They’re checking how you use the site so they can improve it.\n\n- **Improve User Experience**: Cookies help them tailor your experience to make it better.\n\n#### Children’s Privacy\n\nThey’re making it clear that their services aren’t for kids under 13. This is standard practice due to privacy laws, so if you’re under that age, steer clear.\n\n#### Changes to Privacy Policy\n\nHeads up! They mention that this privacy policy could change, and they’ll let users know if something significant changes. So, keep your eyes peeled for updates.\n\n### Contact Info\n\nLastly, they’ve got a way for you to reach out if you have concerns about your privacy. There’s a privacy team you can contact for questions.\n\n### Wrap-Up\n\nSo, AutomateTube is all about making video creation easy with an AI-driven platform. They focus on automating the video-making process, so you can leave the complicated stuff to the AI and focus on your creativity or business needs. They’re upfront about data collection, usage, and security, which is nice. They want to ensure you’re aware of your rights and how they protect your info. \n\nAll in all, if you're looking to dive into the world of video content without all the technical hassle, AutomateTube seems like a solid option to check out. Just go in with your eyes open about what they collect and how they use it, and you should be set!",
  "researchResults": [
    {
      "url": "https://www.youtube.com/watch?v=aol898qC0Oc",
      "content": "No content available",
      "title": "https://www.youtube.com/watch?v=aol898qC0Oc"
    },
    {
      "url": "https://medium.com/@justmcLaughlin/youtubes-new-ai-features-a-game-changer-for-creators-2bf087705b6a",
      "content": "No content available",
      "title": "https://medium.com/@justmcLaughlin/youtubes-new-ai-features-a-game-changer-for-creators-2bf087705b6a"
    },
    {
      "url": "https://techestate.io/youtubes-latest-updates-a-game-changer-for-creators-and-viewers/",
      "content": "No content available",
      "title": "https://techestate.io/youtubes-latest-updates-a-game-changer-for-creators-and-viewers/"
    },
    {
      "url": "https://gc.com/post/automatic-hit-clips",
      "content": "No content available",
      "title": "https://gc.com/post/automatic-hit-clips"
    },
    {
      "url": "https://www.youtube.com/watch?v=iNtS5Z9G5m0",
      "content": "No content available",
      "title": "https://www.youtube.com/watch?v=iNtS5Z9G5m0"
    },
    {
      "url": "https://en.wikipedia.org/wiki/GameChanger",
      "content": "No content available",
      "title": "https://en.wikipedia.org/wiki/GameChanger"
    },
    {
      "url": "https://www.youtube.com/watch?v=bvFqcDNTYrc",
      "content": "No content available",
      "title": "https://www.youtube.com/watch?v=bvFqcDNTYrc"
    },
    {
      "url": "https://neilpatel.com/blog/automated-video-creation/",
      "content": "No content available",
      "title": "https://neilpatel.com/blog/automated-video-creation/"
    }
  ],
  "researchSummary": "Source: https://www.youtube.com/watch?v=aol898qC0Oc\nContent: No content available\n\nSource: https://medium.com/@justmcLaughlin/youtubes-new-ai-features-a-game-changer-for-creators-2bf087705b6a\nContent: No content available\n\nSource: https://techestate.io/youtubes-latest-updates-a-game-changer-for-creators-and-viewers/\nContent: No content available\n\nSource: https://gc.com/post/automatic-hit-clips\nContent: No content available\n\nSource: https://www.youtube.com/watch?v=iNtS5Z9G5m0\nContent: No content available\n\nSource: https://en.wikipedia.org/wiki/GameChanger\nContent: No content available\n\nSource: https://www.youtube.com/watch?v=bvFqcDNTYrc\nContent: No content available\n\nSource: https://neilpatel.com/blog/automated-video-creation/\nContent: No content available",
  "coreTopic": "The main topic of the content is **AutomateTube**, a platform that utilizes AI to simplify video creation. It aims to assist users—such as content creators and marketers—by automating the video production process, allowing them to create videos without the challenges of filming and editing. The content discusses the features of AutomateTube, such as video creation tools and video organization options, while also touching on the type of information collected from users when they sign up for the service.",
  "brandInfo": "\n      automatetube - automatetube - Taglines: None\n    ",
  "youtubeVideo": null,
  "internalLinks": [
    "The provided content does not contain any internal links. It mainly describes the features and purpose of the website AutomateTube without including hyperlinks. If there are specific links you would like to extract or if you have more content with links",
    "please provide that",
    "and I would be happy to help!"
  ],
  "references": [
    "https://www.youtube.com/watch?v=aol898qC0Oc",
    "https://medium.com/@justmcLaughlin/youtubes-new-ai-features-a-game-changer-for-creators-2bf087705b6a",
    "https://techestate.io/youtubes-latest-updates-a-game-changer-for-creators-and-viewers/",
    "https://gc.com/post/automatic-hit-clips",
    "https://www.youtube.com/watch?v=iNtS5Z9G5m0",
    "https://en.wikipedia.org/wiki/GameChanger",
    "https://www.youtube.com/watch?v=bvFqcDNTYrc",
    "https://neilpatel.com/blog/automated-video-creation/",
    "https://help.gc.com/hc/en-us/articles/30437383479565-Uploading-Full-Event-Video-to-GameChanger",
    "https://magnifi.ai/insights/free-sports-highlights-software",
    "https://www.youtube.com/watch?v=ZMhnhniKNWo",
    "https://www.youtube.com/watch?v=78i6qQlfG-c",
    "https://invideo.io/make/games-video-editor/",
    "https://invideo.io/make/online-video-editor/",
    "https://www.kapwing.com/video-editor/gaming"
  ],
  "existingPosts": "",
  "targetKeywords": [],
  "timestamp": "2025-03-17",
  "nudge": "v48a9",
  "extractedKeywords": [
    {
      "keyword": "AI Video Generator",
      "relevance": 9
    },
    {
      "keyword": "Video Creation Tools",
      "relevance": 8
    },
    {
      "keyword": "Automated Video Production",
      "relevance": 7
    },
    {
      "keyword": "Simplify Video Creation",
      "relevance": 8
    },
    {
      "keyword": "Video Organization",
      "relevance": 6
    },
    {
      "keyword": "Content Creator Tools",
      "relevance": 7
    },
    {
      "keyword": "User Data Privacy",
      "relevance": 5
    },
    {
      "keyword": "Video Portfolio Management",
      "relevance": 6
    }
  ]
}